{
  "manifest_id": "GEN-EXP-3DF6A47CF9D4",
  "config": {
    "name": "S3 Coupled: All Safety OFF",
    "hypothesis": "All metabolic and economic safety mechanisms disabled: ATP decay never erodes wealth, treasury never redistributes, children receive 0 ATP at birth, and the extinction floor is removed (no juvenile protection, instant stasis death, populations can reach zero). Under hostile conditions with all adaptation also disabled, this is the maximal coupled invariant violation. Expected: rapid collapse as the population has no recovery mechanism from any perturbation.",
    "sweep": {
      "variable": "SoftCap",
      "start": 30.0,
      "end": 180.0,
      "step": 30.0
    },
    "runs_per_step": 20,
    "epochs_per_run": 500,
    "metrics": [
      "FinalPopulation",
      "Collapsed",
      "SurvivalEpochs",
      "MeanPopulation",
      "MinPopulation",
      "MeanFitness",
      "GiniCoefficient",
      "TotalBirths",
      "TotalDeaths",
      "TreasuryRatio",
      "MaxTreasuryReserve",
      "BirthDeathRatio",
      "AtpVariance",
      "WealthConcentrationIndex",
      "MedianMeanAtpDivergence",
      "MeanGiniCoefficient",
      "MaxGiniCoefficient",
      "ReproductiveInequalityIndex",
      "SurvivalInequalityIndex",
      "TopDecilePersistence"
    ],
    "base_preset": "EarthPrime",
    "base_pressure_override": {
      "soft_cap": 180,
      "entropy_coeff": 0.0001,
      "catastrophe_base_prob": 0.03,
      "catastrophe_pop_scale": 0.00001,
      "gini_wealth_tax_threshold": 1.0,
      "gini_wealth_tax_rate": 0.0,
      "treasury_overflow_threshold": 1.0
    },
    "mutation_rate_override": 0.0,
    "cortex_enabled_override": false,
    "base_stress_override": {
      "skim_rate_multiplier": 1.0,
      "replication_cost_multiplier": 1.0,
      "basal_cost_multiplier": 1.0,
      "catastrophe_cluster_bias": 0.0,
      "mutation_volatility_multiplier": 1.0,
      "treasury_lock_probability": 0.0,
      "treasury_cycling_enabled": false,
      "atp_decay_enabled": false,
      "reproduction_grants_enabled": false,
      "extinction_floor_enabled": false
    },
    "base_seed": 42
  },
  "created_at": "2026-02-24T04:00:52.174310800Z",
  "result_hash": "8d28b766bc67194cc6d7b1a225904d211a650da1b695c304e081d4f3438c6b0b",
  "manifest_hash": "45a55bb76850d4d190bce898bc92e2e9015e5e4113880cf1db0ee16dea4aa8d7",
  "total_worlds": 120,
  "total_epochs": 60000,
  "duration_ms": 2594,
  "findings": [
    "Collapse rate: 0/120 trials (0.0%)",
    "NO COLLAPSES — coupled invariant violation [s3_all_off] did NOT cause extinction",
    "── Inequality Instrumentation ──",
    "Wealth concentration (top 10%): mean=0.4882, max=0.6438",
    "Mean Gini coefficient: mean=0.4567, max=0.6012",
    "Median/Mean ATP divergence: mean=0.4173, max=0.6750",
    "  ⚠ RIGHT-SKEWED: Mean >> Median, wealth hoarding",
    "ATP variance: mean=1561.3, max=7358.0",
    "Reproductive inequality: mean=0.8653, max=0.9583",
    "  ⚠ REPRODUCTIVE MONOPOLY: Top quartile >50% of births",
    "Survival inequality: mean=0.8923, max=0.9435",
    "  ⚠ SURVIVAL APARTHEID: Bottom quartile >50% of deaths",
    "Top decile persistence: mean=0.1103, max=0.7940",
    "── Population & Economy ──",
    "Population floor: global_min=20, mean_min=20.0",
    "Mean population: 38.9 (min trial: 29.0)",
    "Final population: mean=44.6, min=28, max=52",
    "Birth/death ratio: mean=0.9884, min=0.6667",
    "Total births: mean=143.0, min=40",
    "Treasury accumulation: global_max=1667.1, mean_max=485.3 ATP",
    "Mean fitness: 0.5906",
    "── Per-step breakdown ──",
    "  cap=30: collapse=0.0%, pop=29.5, gini=0.5584, wci=0.4662, repro=0.5737, surv=0.7619",
    "  cap=60: collapse=0.0%, pop=41.2, gini=0.4481, wci=0.5336, repro=0.9105, surv=0.9125",
    "  cap=90: collapse=0.0%, pop=40.6, gini=0.4313, wci=0.4625, repro=0.9253, surv=0.9175",
    "  cap=120: collapse=0.0%, pop=40.9, gini=0.4233, wci=0.4987, repro=0.9317, surv=0.9225",
    "  cap=150: collapse=0.0%, pop=40.5, gini=0.4384, wci=0.4839, repro=0.9249, surv=0.9186",
    "  cap=180: collapse=0.0%, pop=40.7, gini=0.4410, wci=0.4845, repro=0.9258, surv=0.9211",
    "── VERDICT ──",
    "NO COLLAPSE but PATHOLOGICAL: [s3_all_off] → [wealth_concentration=0.488, repro_inequality=0.865, survival_inequality=0.892]",
    "Survivable but degenerate economy under coupled invariant violation"
  ],
  "protocol_version": "0.1.0"
}