{
  "manifest_id": "GEN-EXP-07B6DE7EA42C",
  "config": {
    "name": "S4 Topology: Extended Horizon (5000 epochs)",
    "hypothesis": "With zero regeneration and death sink over 5,000 epochs (10× standard), slow resource depletion should eventually exhaust all pools. Even if 500 epochs isn't enough to collapse, 5,000 should be. This tests the slow-death hypothesis: does the system find a stable equilibrium at depleted pools, or does it eventually flatline?",
    "sweep": {
      "variable": "SoftCap",
      "start": 30.0,
      "end": 180.0,
      "step": 30.0
    },
    "runs_per_step": 10,
    "epochs_per_run": 5000,
    "metrics": [
      "FinalPopulation",
      "Collapsed",
      "SurvivalEpochs",
      "MeanPopulation",
      "MinPopulation",
      "MeanFitness",
      "GiniCoefficient",
      "TotalBirths",
      "TotalDeaths",
      "TreasuryRatio",
      "MaxTreasuryReserve",
      "BirthDeathRatio",
      "AtpVariance",
      "WealthConcentrationIndex",
      "MedianMeanAtpDivergence",
      "MeanGiniCoefficient",
      "MaxGiniCoefficient",
      "ReproductiveInequalityIndex",
      "SurvivalInequalityIndex",
      "TopDecilePersistence"
    ],
    "base_preset": "EarthPrime",
    "base_pressure_override": {
      "soft_cap": 180,
      "entropy_coeff": 0.0001,
      "catastrophe_base_prob": 0.03,
      "catastrophe_pop_scale": 0.00001,
      "gini_wealth_tax_threshold": 1.0,
      "gini_wealth_tax_rate": 0.0,
      "treasury_overflow_threshold": 1.0
    },
    "mutation_rate_override": 0.0,
    "cortex_enabled_override": false,
    "base_stress_override": {
      "skim_rate_multiplier": 1.0,
      "replication_cost_multiplier": 1.0,
      "basal_cost_multiplier": 1.0,
      "catastrophe_cluster_bias": 0.0,
      "mutation_volatility_multiplier": 1.0,
      "treasury_lock_probability": 0.0,
      "treasury_cycling_enabled": true,
      "atp_decay_enabled": true,
      "reproduction_grants_enabled": true,
      "extinction_floor_enabled": true,
      "resource_regeneration_enabled": false,
      "death_drains_resources": true
    },
    "base_seed": 42
  },
  "created_at": "2026-02-24T04:23:47.347511600Z",
  "result_hash": "b59376ffc262dd1f4f140e9710e4263d0163affdc32f9c60a93afc1ec7d3ac2e",
  "manifest_hash": "fef89aa178daa34427676fa4cd8d40992a107d7d83691c6897a37c2462f6662f",
  "total_worlds": 60,
  "total_epochs": 300000,
  "duration_ms": 32578,
  "findings": [
    "Collapse rate: 0/60 trials (0.0%)",
    "NO COLLAPSES — topology violation [s4_extended_horizon] did NOT cause extinction",
    "── Resource Topology ──",
    "── Inequality Instrumentation ──",
    "Wealth concentration (top 10%): mean=0.3182, max=0.5474",
    "Mean Gini coefficient: mean=0.6077, max=0.6566",
    "  ⚠ SEVERE INEQUALITY: Gini > 0.6",
    "Median/Mean ATP divergence: mean=0.2224, max=0.5645",
    "ATP variance: mean=15.9, max=73.6",
    "Reproductive inequality: mean=0.9968, max=0.9982",
    "  ⚠ REPRODUCTIVE MONOPOLY: Top quartile >50% of births",
    "Survival inequality: mean=0.9538, max=0.9558",
    "  ⚠ SURVIVAL APARTHEID: Bottom quartile >50% of deaths",
    "Top decile persistence: mean=0.3983, max=0.6156",
    "── Population & Economy ──",
    "Population floor: global_min=7, mean_min=12.0",
    "Mean population: 26.0 (min trial: 24.0)",
    "Final population: mean=26.6, min=22, max=31",
    "Birth/death ratio: mean=0.9461, min=0.8475",
    "Total births: mean=2153.2, min=1951",
    "Treasury accumulation: global_max=6.4, mean_max=2.9 ATP",
    "Mean fitness: 0.5188",
    "── Per-step breakdown ──",
    "  cap=30: collapse=0.0%, pop=24.4, gini=0.6454, wci=0.4266, repro=0.9969, surv=0.9500",
    "  cap=60: collapse=0.0%, pop=26.5, gini=0.5990, wci=0.2908, repro=0.9969, surv=0.9548",
    "  cap=90: collapse=0.0%, pop=26.2, gini=0.6010, wci=0.2811, repro=0.9969, surv=0.9543",
    "  cap=120: collapse=0.0%, pop=26.4, gini=0.5992, wci=0.3065, repro=0.9970, surv=0.9547",
    "  cap=150: collapse=0.0%, pop=26.3, gini=0.5993, wci=0.3005, repro=0.9965, surv=0.9547",
    "  cap=180: collapse=0.0%, pop=26.2, gini=0.6024, wci=0.3040, repro=0.9967, surv=0.9544",
    "── VERDICT ──",
    "NO COLLAPSE but PATHOLOGICAL: [s4_extended_horizon] → [gini=0.608, repro_inequality=0.997, survival_inequality=0.954]",
    "Survivable but degenerate economy under topology violation"
  ],
  "protocol_version": "0.1.0"
}